langgraph/checkpoint/tablestore/__init__.py
langgraph/checkpoint/tablestore/py.typed
langgraph/checkpoint/tablestore/saver.py
langgraph/store/tablestore/__init__.py
langgraph/store/tablestore/py.typed
langgraph/store/tablestore/store.py
langgraph_checkpoint_tablestore-0.1.0.dist-info/METADATA
langgraph_checkpoint_tablestore-0.1.0.dist-info/WHEEL
langgraph_checkpoint_tablestore-0.1.0.dist-info/RECORD
