Metadata-Version: 2.4
Name: langgraph-checkpoint-tablestore
Version: 0.1.0
Summary: Library with a Tablestore implementation of LangGraph checkpoint saver.
Author-email: Louis Bao <louis.bao@qq.com>
Requires-Python: >=3.9
Requires-Dist: langgraph-checkpoint>=2.0.23
Requires-Dist: tablestore>=6.2.0
